ib_syncevent/IBHelpers.py
ib_syncevent/IBSyncEvent.py
ib_syncevent/__init__.py
ib_syncevent/utilities/Enums.py
ib_syncevent/utilities/IBApi.py
ib_syncevent/utilities/IBDataReciver.py
ib_syncevent/utilities/IBEvents.py
ib_syncevent/utilities/__init__.py
ib_syncevent-0.0.35.dist-info/LICENSE
ib_syncevent-0.0.35.dist-info/METADATA
ib_syncevent-0.0.35.dist-info/WHEEL
ib_syncevent-0.0.35.dist-info/top_level.txt
ib_syncevent-0.0.35.dist-info/RECORD
