Metadata-Version: 2.1
Name: ib-syncevent
Version: 0.0.35
Summary: Get financial data synchronously. This package is a wrapper around the IB API.
Home-page: UNKNOWN
Author: Zohar
Author-email: <mail@test.com>
License: UNKNOWN
Keywords: python,ib,financial,financial data,stcoks
Platform: UNKNOWN
Classifier: Development Status :: 1 - Planning
Classifier: Intended Audience :: Developers
Classifier: Programming Language :: Python :: 3
Classifier: Operating System :: Unix
Classifier: Operating System :: MacOS :: MacOS X
Classifier: Operating System :: Microsoft :: Windows
Requires-Python: >=3.8
Requires-Dist: ibapi
